yt_concate/__init__.py
yt_concate/log.py
yt_concate/main.py
yt_concate/settings.py
yt_concate/utils.py
yt_concate/model/__init__.py
yt_concate/model/found.py
yt_concate/model/yt.py
yt_concate/pipeline/__init__.py
yt_concate/pipeline/pipeline.py
yt_concate/pipeline/steps/__init__.py
yt_concate/pipeline/steps/download_video.py
yt_concate/pipeline/steps/edit_video.py
yt_concate/pipeline/steps/get_video_captions.py
yt_concate/pipeline/steps/get_video_links.py
yt_concate/pipeline/steps/initialize_yt.py
yt_concate/pipeline/steps/postflight.py
yt_concate/pipeline/steps/preflight.py
yt_concate/pipeline/steps/search_term.py
yt_concate/pipeline/steps/step.py
yout_concate-0.1.2.dist-info/LICENSE
yout_concate-0.1.2.dist-info/METADATA
yout_concate-0.1.2.dist-info/WHEEL
yout_concate-0.1.2.dist-info/top_level.txt
yout_concate-0.1.2.dist-info/RECORD
