Metadata-Version: 2.1
Name: yout-concate
Version: 0.1.2
Summary: Produce a concatenated video of clips that mentioned a word from a youtube channel.
Home-page: https://github.com/ThatMrWayne/yout_concate
Author: Wayne Hsu
Author-email: whph60308@gmail.com
License: MIT
Platform: UNKNOWN
Classifier: License :: OSI Approved :: MIT License
Classifier: Programming Language :: Python
Classifier: Programming Language :: Python :: 3
Classifier: Programming Language :: Python :: 3.6
Classifier: Programming Language :: Python :: Implementation :: CPython
Classifier: Programming Language :: Python :: Implementation :: PyPy
Requires-Python: >=3.8.0
License-File: LICENSE
Requires-Dist: moviepy
Requires-Dist: pytube
Requires-Dist: requests
Requires-Dist: python-dotenv
Requires-Dist: urllib3
Requires-Dist: youtube-transcript-api
